LICENSE.txt
MANIFEST.in
README.txt
setup.py
pcart_catalog/__init__.py
pcart_catalog/admin.py
pcart_catalog/apps.py
pcart_catalog/cms_apps.py
pcart_catalog/cms_menus.py
pcart_catalog/cms_plugins.py
pcart_catalog/cms_toolbars.py
pcart_catalog/cms_wizards.py
pcart_catalog/filtering.py
pcart_catalog/forms.py
pcart_catalog/models.py
pcart_catalog/settings.py
pcart_catalog/signals.py
pcart_catalog/sitemap.py
pcart_catalog/tasks.py
pcart_catalog/thumbnail_processors.py
pcart_catalog/triggers.py
pcart_catalog/urls_collection.py
pcart_catalog/urls_product.py
pcart_catalog/utils.py
pcart_catalog/views.py
pcart_catalog.egg-info/PKG-INFO
pcart_catalog.egg-info/SOURCES.txt
pcart_catalog.egg-info/dependency_links.txt
pcart_catalog.egg-info/not-zip-safe
pcart_catalog.egg-info/requires.txt
pcart_catalog.egg-info/top_level.txt
pcart_catalog/locale/ru/LC_MESSAGES/django.mo
pcart_catalog/locale/ru/LC_MESSAGES/django.po
pcart_catalog/locale/uk/LC_MESSAGES/django.mo
pcart_catalog/locale/uk/LC_MESSAGES/django.po
pcart_catalog/migrations/0001_initial.py
pcart_catalog/migrations/0002_auto_20170209_2130.py
pcart_catalog/migrations/0003_auto_20170209_2135.py
pcart_catalog/migrations/0004_auto_20170220_2032.py
pcart_catalog/migrations/0005_auto_20170220_2047.py
pcart_catalog/migrations/0006_productimage_download_link.py
pcart_catalog/migrations/0007_auto_20170309_1144.py
pcart_catalog/migrations/0008_productimage_downloaded.py
pcart_catalog/migrations/0009_collectionpluginmodel.py
pcart_catalog/migrations/0010_auto_20170326_1953.py
pcart_catalog/migrations/0011_auto_20170326_1955.py
pcart_catalog/migrations/0012_remove_collection_exclude_properties_filters.py
pcart_catalog/migrations/0013_collection_exclude_properties_filters.py
pcart_catalog/migrations/0014_auto_20170411_1025.py
pcart_catalog/migrations/0015_vendor_slug.py
pcart_catalog/migrations/0016_auto_20170425_1320.py
pcart_catalog/migrations/0017_auto_20170425_1325.py
pcart_catalog/migrations/0018_propertyvalueslug.py
pcart_catalog/migrations/0019_auto_20170505_1202.py
pcart_catalog/migrations/0020_auto_20170808_1104.py
pcart_catalog/migrations/0021_collection_custom_url_filter_rules.py
pcart_catalog/migrations/0022_auto_20170814_1258.py
